growwmcp/__init__.py
growwmcp/__main__.py
growwmcp/main.py
growwmcp/utils/__init__.py
growwmcp/utils/helper.py
growwmcp/utils/indicator_helper.py
growwmcp/utils/pattern_helper.py
growwmcp/utils/prompt_lib.py
growwmcp/utils/prompts/__init__.py
growwmcp/utils/prompts/system.py
growwmcp/utils/tools/__init__.py
growwmcp/utils/tools/feed.py
growwmcp/utils/tools/historicaldata.py
growwmcp/utils/tools/indicators.py
growwmcp/utils/tools/instruments.py
growwmcp/utils/tools/livedata.py
growwmcp/utils/tools/margins.py
growwmcp/utils/tools/orders.py
growwmcp/utils/tools/pattern.py
growwmcp/utils/tools/portfolio.py
growwmcp/utils/tools/utils.py
growwmcp-0.1.12.dist-info/METADATA
growwmcp-0.1.12.dist-info/WHEEL
growwmcp-0.1.12.dist-info/entry_points.txt
growwmcp-0.1.12.dist-info/top_level.txt
growwmcp-0.1.12.dist-info/RECORD
