Metadata-Version: 2.4
Name: growwmcp
Version: 0.1.12
Summary: Groww MCP package
Home-page: https://github.com/Groww/ml-growwmcp
Author: Sayan Dey
Author-email: sayand@groww.in
Requires-Python: >=3.10
Requires-Dist: fastmcp==2.9.2
Requires-Dist: pandas==2.3.0
Requires-Dist: pydantic==2.11.7
Requires-Dist: pyyaml==6.0.2
Requires-Dist: requests==2.32.4
Requires-Dist: growwapi==0.0.8
Requires-Dist: pyotp==2.9.0
Requires-Dist: jinja2==3.0.2
Requires-Dist: numpy>=1.21.0
Dynamic: author
Dynamic: author-email
Dynamic: description
Dynamic: description-content-type
Dynamic: home-page
Dynamic: requires-dist
Dynamic: requires-python
Dynamic: summary
